{
  "frames": {
    "stone_upper_left_corner": {
      "frame": { "x": 0, "y": 0, "w": 16, "h": 16 },
      "rotated": false,
      "trimmed": false,
      "spriteSourceSize": { "x": 0, "y": 0, "w": 16, "h": 16 },
      "sourceSize": { "w": 16, "h": 16 }
    },
    "stone_top": {
      "frame": { "x": 16, "y": 0, "w": 16, "h": 16 },
      "rotated": false,
      "trimmed": false,
      "spriteSourceSize": { "x": 0, "y": 0, "w": 16, "h": 16 },
      "sourceSize": { "w": 16, "h": 16 }
    },
    "stone_upper_right_corner": {
      "frame": { "x": 32, "y": 0, "w": 16, "h": 16 },
      "rotated": false,
      "trimmed": false,
      "spriteSourceSize": { "x": 0, "y": 0, "w": 16, "h": 16 },
      "sourceSize": { "w": 16, "h": 16 }
    },
    "sprite17": {
      "frame": { "x": 48, "y": 0, "w": 16, "h": 16 },
      "rotated": false,
      "trimmed": false,
      "spriteSourceSize": { "x": 0, "y": 0, "w": 16, "h": 16 },
      "sourceSize": { "w": 16, "h": 16 }
    },
    "sprite18": {
      "frame": { "x": 64, "y": 0, "w": 16, "h": 16 },
      "rotated": false,
      "trimmed": false,
      "spriteSourceSize": { "x": 0, "y": 0, "w": 16, "h": 16 },
      "sourceSize": { "w": 16, "h": 16 }
    },
    "grass_floor_1": {
      "frame": { "x": 96, "y": 0, "w": 16, "h": 16 },
      "rotated": false,
      "trimmed": false,
      "spriteSourceSize": { "x": 0, "y": 0, "w": 16, "h": 16 },
      "sourceSize": { "w": 16, "h": 16 }
    },
    "grass_floor_2": {
      "frame": { "x": 112, "y": 0, "w": 16, "h": 16 },
      "rotated": false,
      "trimmed": false,
      "spriteSourceSize": { "x": 0, "y": 0, "w": 16, "h": 16 },
      "sourceSize": { "w": 16, "h": 16 }
    },
    "grass_floor_3": {
      "frame": { "x": 128, "y": 0, "w": 16, "h": 16 },
      "rotated": false,
      "trimmed": false,
      "spriteSourceSize": { "x": 0, "y": 0, "w": 16, "h": 16 },
      "sourceSize": { "w": 16, "h": 16 }
    },
    "glass_floor_upper_left": {
      "frame": { "x": 144, "y": 0, "w": 16, "h": 16 },
      "rotated": false,
      "trimmed": false,
      "spriteSourceSize": { "x": 0, "y": 0, "w": 16, "h": 16 },
      "sourceSize": { "w": 16, "h": 16 }
    },
    "glass_floor_upper_right": {
      "frame": { "x": 160, "y": 0, "w": 16, "h": 16 },
      "rotated": false,
      "trimmed": false,
      "spriteSourceSize": { "x": 0, "y": 0, "w": 16, "h": 16 },
      "sourceSize": { "w": 16, "h": 16 }
    },
    "copper_brick_h_1": {
      "frame": { "x": 192, "y": 0, "w": 16, "h": 16 },
      "rotated": false,
      "trimmed": false,
      "spriteSourceSize": { "x": 0, "y": 0, "w": 16, "h": 16 },
      "sourceSize": { "w": 16, "h": 16 }
    },
    "copper_brick_h_2": {
      "frame": { "x": 208, "y": 0, "w": 16, "h": 16 },
      "rotated": false,
      "trimmed": false,
      "spriteSourceSize": { "x": 0, "y": 0, "w": 16, "h": 16 },
      "sourceSize": { "w": 16, "h": 16 }
    },
    "copper_brick_h_3": {
      "frame": { "x": 224, "y": 0, "w": 16, "h": 16 },
      "rotated": false,
      "trimmed": false,
      "spriteSourceSize": { "x": 0, "y": 0, "w": 16, "h": 16 },
      "sourceSize": { "w": 16, "h": 16 }
    },
    "copper_brick_v_1": {
      "frame": { "x": 240, "y": 0, "w": 16, "h": 16 },
      "rotated": false,
      "trimmed": false,
      "spriteSourceSize": { "x": 0, "y": 0, "w": 16, "h": 16 },
      "sourceSize": { "w": 16, "h": 16 }
    },
    "gold_floor_1": {
      "frame": { "x": 272, "y": 0, "w": 16, "h": 16 },
      "rotated": false,
      "trimmed": false,
      "spriteSourceSize": { "x": 0, "y": 0, "w": 16, "h": 16 },
      "sourceSize": { "w": 16, "h": 16 }
    },
    "gold_floor_2": {
      "frame": { "x": 288, "y": 0, "w": 16, "h": 16 },
      "rotated": false,
      "trimmed": false,
      "spriteSourceSize": { "x": 0, "y": 0, "w": 16, "h": 16 },
      "sourceSize": { "w": 16, "h": 16 }
    },
    "gold_floor_3": {
      "frame": { "x": 304, "y": 0, "w": 16, "h": 16 },
      "rotated": false,
      "trimmed": false,
      "spriteSourceSize": { "x": 0, "y": 0, "w": 16, "h": 16 },
      "sourceSize": { "w": 16, "h": 16 }
    },
    "stone_left": {
      "frame": { "x": 0, "y": 16, "w": 16, "h": 16 },
      "rotated": false,
      "trimmed": false,
      "spriteSourceSize": { "x": 0, "y": 0, "w": 16, "h": 16 },
      "sourceSize": { "w": 16, "h": 16 }
    },
    "sprite32": {
      "frame": { "x": 16, "y": 16, "w": 16, "h": 16 },
      "rotated": false,
      "trimmed": false,
      "spriteSourceSize": { "x": 0, "y": 0, "w": 16, "h": 16 },
      "sourceSize": { "w": 16, "h": 16 }
    },
    "stone_right": {
      "frame": { "x": 32, "y": 16, "w": 16, "h": 16 },
      "rotated": false,
      "trimmed": false,
      "spriteSourceSize": { "x": 0, "y": 0, "w": 16, "h": 16 },
      "sourceSize": { "w": 16, "h": 16 }
    },
    "sprite34": {
      "frame": { "x": 48, "y": 16, "w": 16, "h": 16 },
      "rotated": false,
      "trimmed": false,
      "spriteSourceSize": { "x": 0, "y": 0, "w": 16, "h": 16 },
      "sourceSize": { "w": 16, "h": 16 }
    },
    "sprite35": {
      "frame": { "x": 64, "y": 16, "w": 16, "h": 16 },
      "rotated": false,
      "trimmed": false,
      "spriteSourceSize": { "x": 0, "y": 0, "w": 16, "h": 16 },
      "sourceSize": { "w": 16, "h": 16 }
    },
    "grass_floor_4": {
      "frame": { "x": 96, "y": 16, "w": 16, "h": 16 },
      "rotated": false,
      "trimmed": false,
      "spriteSourceSize": { "x": 0, "y": 0, "w": 16, "h": 16 },
      "sourceSize": { "w": 16, "h": 16 }
    },
    "grass_floor_5": {
      "frame": { "x": 112, "y": 16, "w": 16, "h": 16 },
      "rotated": false,
      "trimmed": false,
      "spriteSourceSize": { "x": 0, "y": 0, "w": 16, "h": 16 },
      "sourceSize": { "w": 16, "h": 16 }
    },
    "grass_floor_6": {
      "frame": { "x": 128, "y": 16, "w": 16, "h": 16 },
      "rotated": false,
      "trimmed": false,
      "spriteSourceSize": { "x": 0, "y": 0, "w": 16, "h": 16 },
      "sourceSize": { "w": 16, "h": 16 }
    },
    "glass_floor_lower_left": {
      "frame": { "x": 144, "y": 16, "w": 16, "h": 16 },
      "rotated": false,
      "trimmed": false,
      "spriteSourceSize": { "x": 0, "y": 0, "w": 16, "h": 16 },
      "sourceSize": { "w": 16, "h": 16 }
    },
    "glass_floor_lower_right": {
      "frame": { "x": 160, "y": 16, "w": 16, "h": 16 },
      "rotated": false,
      "trimmed": false,
      "spriteSourceSize": { "x": 0, "y": 0, "w": 16, "h": 16 },
      "sourceSize": { "w": 16, "h": 16 }
    },
    "copper_brick_mini": {
      "frame": { "x": 192, "y": 16, "w": 16, "h": 16 },
      "rotated": false,
      "trimmed": false,
      "spriteSourceSize": { "x": 0, "y": 0, "w": 16, "h": 16 },
      "sourceSize": { "w": 16, "h": 16 }
    },
    "copper_brick_upper_left": {
      "frame": { "x": 208, "y": 16, "w": 16, "h": 16 },
      "rotated": false,
      "trimmed": false,
      "spriteSourceSize": { "x": 0, "y": 0, "w": 16, "h": 16 },
      "sourceSize": { "w": 16, "h": 16 }
    },
    "copper_brick_upper_right": {
      "frame": { "x": 224, "y": 16, "w": 16, "h": 16 },
      "rotated": false,
      "trimmed": false,
      "spriteSourceSize": { "x": 0, "y": 0, "w": 16, "h": 16 },
      "sourceSize": { "w": 16, "h": 16 }
    },
    "copper_brick_v_2": {
      "frame": { "x": 240, "y": 16, "w": 16, "h": 16 },
      "rotated": false,
      "trimmed": false,
      "spriteSourceSize": { "x": 0, "y": 0, "w": 16, "h": 16 },
      "sourceSize": { "w": 16, "h": 16 }
    },
    "wood_floor_1": {
      "frame": { "x": 272, "y": 16, "w": 16, "h": 16 },
      "rotated": false,
      "trimmed": false,
      "spriteSourceSize": { "x": 0, "y": 0, "w": 16, "h": 16 },
      "sourceSize": { "w": 16, "h": 16 }
    },
    "wood_floor_2": {
      "frame": { "x": 288, "y": 16, "w": 16, "h": 16 },
      "rotated": false,
      "trimmed": false,
      "spriteSourceSize": { "x": 0, "y": 0, "w": 16, "h": 16 },
      "sourceSize": { "w": 16, "h": 16 }
    },
    "wood_floor_3": {
      "frame": { "x": 304, "y": 16, "w": 16, "h": 16 },
      "rotated": false,
      "trimmed": false,
      "spriteSourceSize": { "x": 0, "y": 0, "w": 16, "h": 16 },
      "sourceSize": { "w": 16, "h": 16 }
    },
    "stone_lower_left_corner": {
      "frame": { "x": 0, "y": 32, "w": 16, "h": 16 },
      "rotated": false,
      "trimmed": false,
      "spriteSourceSize": { "x": 0, "y": 0, "w": 16, "h": 16 },
      "sourceSize": { "w": 16, "h": 16 }
    },
    "stone_bottom": {
      "frame": { "x": 16, "y": 32, "w": 16, "h": 16 },
      "rotated": false,
      "trimmed": false,
      "spriteSourceSize": { "x": 0, "y": 0, "w": 16, "h": 16 },
      "sourceSize": { "w": 16, "h": 16 }
    },
    "stone_lower_right_corner": {
      "frame": { "x": 32, "y": 32, "w": 16, "h": 16 },
      "rotated": false,
      "trimmed": false,
      "spriteSourceSize": { "x": 0, "y": 0, "w": 16, "h": 16 },
      "sourceSize": { "w": 16, "h": 16 }
    },
    "grass_floor_7": {
      "frame": { "x": 96, "y": 32, "w": 16, "h": 16 },
      "rotated": false,
      "trimmed": false,
      "spriteSourceSize": { "x": 0, "y": 0, "w": 16, "h": 16 },
      "sourceSize": { "w": 16, "h": 16 }
    },
    "grass_floor_8": {
      "frame": { "x": 112, "y": 32, "w": 16, "h": 16 },
      "rotated": false,
      "trimmed": false,
      "spriteSourceSize": { "x": 0, "y": 0, "w": 16, "h": 16 },
      "sourceSize": { "w": 16, "h": 16 }
    },
    "grass_floor_9": {
      "frame": { "x": 128, "y": 32, "w": 16, "h": 16 },
      "rotated": false,
      "trimmed": false,
      "spriteSourceSize": { "x": 0, "y": 0, "w": 16, "h": 16 },
      "sourceSize": { "w": 16, "h": 16 }
    },
    "copper_brick_lower_left": {
      "frame": { "x": 208, "y": 32, "w": 16, "h": 16 },
      "rotated": false,
      "trimmed": false,
      "spriteSourceSize": { "x": 0, "y": 0, "w": 16, "h": 16 },
      "sourceSize": { "w": 16, "h": 16 }
    },
    "copper_brick_lower_right": {
      "frame": { "x": 224, "y": 32, "w": 16, "h": 16 },
      "rotated": false,
      "trimmed": false,
      "spriteSourceSize": { "x": 0, "y": 0, "w": 16, "h": 16 },
      "sourceSize": { "w": 16, "h": 16 }
    },
    "copper_brick_v_3": {
      "frame": { "x": 240, "y": 32, "w": 16, "h": 16 },
      "rotated": false,
      "trimmed": false,
      "spriteSourceSize": { "x": 0, "y": 0, "w": 16, "h": 16 },
      "sourceSize": { "w": 16, "h": 16 }
    },
    "metal_floor_1": {
      "frame": { "x": 272, "y": 32, "w": 16, "h": 16 },
      "rotated": false,
      "trimmed": false,
      "spriteSourceSize": { "x": 0, "y": 0, "w": 16, "h": 16 },
      "sourceSize": { "w": 16, "h": 16 }
    },
    "metal_floor_2": {
      "frame": { "x": 288, "y": 32, "w": 16, "h": 16 },
      "rotated": false,
      "trimmed": false,
      "spriteSourceSize": { "x": 0, "y": 0, "w": 16, "h": 16 },
      "sourceSize": { "w": 16, "h": 16 }
    },
    "metal_floor_3": {
      "frame": { "x": 304, "y": 32, "w": 16, "h": 16 },
      "rotated": false,
      "trimmed": false,
      "spriteSourceSize": { "x": 0, "y": 0, "w": 16, "h": 16 },
      "sourceSize": { "w": 16, "h": 16 }
    },
    "wood_upper_left_corner": {
      "frame": { "x": 0, "y": 64, "w": 16, "h": 16 },
      "rotated": false,
      "trimmed": false,
      "spriteSourceSize": { "x": 0, "y": 0, "w": 16, "h": 16 },
      "sourceSize": { "w": 16, "h": 16 }
    },
    "wood_top": {
      "frame": { "x": 16, "y": 64, "w": 16, "h": 16 },
      "rotated": false,
      "trimmed": false,
      "spriteSourceSize": { "x": 0, "y": 0, "w": 16, "h": 16 },
      "sourceSize": { "w": 16, "h": 16 }
    },
    "wood_upper_right_corner": {
      "frame": { "x": 32, "y": 64, "w": 16, "h": 16 },
      "rotated": false,
      "trimmed": false,
      "spriteSourceSize": { "x": 0, "y": 0, "w": 16, "h": 16 },
      "sourceSize": { "w": 16, "h": 16 }
    },
    "sprite63": {
      "frame": { "x": 48, "y": 64, "w": 16, "h": 16 },
      "rotated": false,
      "trimmed": false,
      "spriteSourceSize": { "x": 0, "y": 0, "w": 16, "h": 16 },
      "sourceSize": { "w": 16, "h": 16 }
    },
    "sprite64": {
      "frame": { "x": 64, "y": 64, "w": 16, "h": 16 },
      "rotated": false,
      "trimmed": false,
      "spriteSourceSize": { "x": 0, "y": 0, "w": 16, "h": 16 },
      "sourceSize": { "w": 16, "h": 16 }
    },
    "orange_floor_1": {
      "frame": { "x": 96, "y": 64, "w": 16, "h": 16 },
      "rotated": false,
      "trimmed": false,
      "spriteSourceSize": { "x": 0, "y": 0, "w": 16, "h": 16 },
      "sourceSize": { "w": 16, "h": 16 }
    },
    "orange_floor_2": {
      "frame": { "x": 112, "y": 64, "w": 16, "h": 16 },
      "rotated": false,
      "trimmed": false,
      "spriteSourceSize": { "x": 0, "y": 0, "w": 16, "h": 16 },
      "sourceSize": { "w": 16, "h": 16 }
    },
    "orange_floor_3": {
      "frame": { "x": 128, "y": 64, "w": 16, "h": 16 },
      "rotated": false,
      "trimmed": false,
      "spriteSourceSize": { "x": 0, "y": 0, "w": 16, "h": 16 },
      "sourceSize": { "w": 16, "h": 16 }
    },
    "orange_floor_upper_left": {
      "frame": { "x": 144, "y": 64, "w": 16, "h": 16 },
      "rotated": false,
      "trimmed": false,
      "spriteSourceSize": { "x": 0, "y": 0, "w": 16, "h": 16 },
      "sourceSize": { "w": 16, "h": 16 }
    },
    "orange_floor_upper_right": {
      "frame": { "x": 160, "y": 64, "w": 16, "h": 16 },
      "rotated": false,
      "trimmed": false,
      "spriteSourceSize": { "x": 0, "y": 0, "w": 16, "h": 16 },
      "sourceSize": { "w": 16, "h": 16 }
    },
    "metal_brick_h_1": {
      "frame": { "x": 192, "y": 64, "w": 16, "h": 16 },
      "rotated": false,
      "trimmed": false,
      "spriteSourceSize": { "x": 0, "y": 0, "w": 16, "h": 16 },
      "sourceSize": { "w": 16, "h": 16 }
    },
    "metal_brick_h_2": {
      "frame": { "x": 208, "y": 64, "w": 16, "h": 16 },
      "rotated": false,
      "trimmed": false,
      "spriteSourceSize": { "x": 0, "y": 0, "w": 16, "h": 16 },
      "sourceSize": { "w": 16, "h": 16 }
    },
    "metal_brick_h_3": {
      "frame": { "x": 224, "y": 64, "w": 16, "h": 16 },
      "rotated": false,
      "trimmed": false,
      "spriteSourceSize": { "x": 0, "y": 0, "w": 16, "h": 16 },
      "sourceSize": { "w": 16, "h": 16 }
    },
    "metal_brick_v_1": {
      "frame": { "x": 240, "y": 64, "w": 16, "h": 16 },
      "rotated": false,
      "trimmed": false,
      "spriteSourceSize": { "x": 0, "y": 0, "w": 16, "h": 16 },
      "sourceSize": { "w": 16, "h": 16 }
    },
    "brick_1": {
      "frame": { "x": 272, "y": 64, "w": 16, "h": 16 },
      "rotated": false,
      "trimmed": false,
      "spriteSourceSize": { "x": 0, "y": 0, "w": 16, "h": 16 },
      "sourceSize": { "w": 16, "h": 16 }
    },
    "brick_2": {
      "frame": { "x": 288, "y": 64, "w": 16, "h": 16 },
      "rotated": false,
      "trimmed": false,
      "spriteSourceSize": { "x": 0, "y": 0, "w": 16, "h": 16 },
      "sourceSize": { "w": 16, "h": 16 }
    },
    "brick_3": {
      "frame": { "x": 304, "y": 64, "w": 16, "h": 16 },
      "rotated": false,
      "trimmed": false,
      "spriteSourceSize": { "x": 0, "y": 0, "w": 16, "h": 16 },
      "sourceSize": { "w": 16, "h": 16 }
    },
    "sprite77": {
      "frame": { "x": 320, "y": 64, "w": 16, "h": 16 },
      "rotated": false,
      "trimmed": false,
      "spriteSourceSize": { "x": 0, "y": 0, "w": 16, "h": 16 },
      "sourceSize": { "w": 16, "h": 16 }
    },
    "sprite78": {
      "frame": { "x": 336, "y": 64, "w": 16, "h": 16 },
      "rotated": false,
      "trimmed": false,
      "spriteSourceSize": { "x": 0, "y": 0, "w": 16, "h": 16 },
      "sourceSize": { "w": 16, "h": 16 }
    },
    "wood_left": {
      "frame": { "x": 0, "y": 80, "w": 16, "h": 16 },
      "rotated": false,
      "trimmed": false,
      "spriteSourceSize": { "x": 0, "y": 0, "w": 16, "h": 16 },
      "sourceSize": { "w": 16, "h": 16 }
    },
    "sprite80": {
      "frame": { "x": 16, "y": 80, "w": 16, "h": 16 },
      "rotated": false,
      "trimmed": false,
      "spriteSourceSize": { "x": 0, "y": 0, "w": 16, "h": 16 },
      "sourceSize": { "w": 16, "h": 16 }
    },
    "wood_right": {
      "frame": { "x": 32, "y": 80, "w": 16, "h": 16 },
      "rotated": false,
      "trimmed": false,
      "spriteSourceSize": { "x": 0, "y": 0, "w": 16, "h": 16 },
      "sourceSize": { "w": 16, "h": 16 }
    },
    "sprite82": {
      "frame": { "x": 48, "y": 80, "w": 16, "h": 16 },
      "rotated": false,
      "trimmed": false,
      "spriteSourceSize": { "x": 0, "y": 0, "w": 16, "h": 16 },
      "sourceSize": { "w": 16, "h": 16 }
    },
    "sprite83": {
      "frame": { "x": 64, "y": 80, "w": 16, "h": 16 },
      "rotated": false,
      "trimmed": false,
      "spriteSourceSize": { "x": 0, "y": 0, "w": 16, "h": 16 },
      "sourceSize": { "w": 16, "h": 16 }
    },
    "orange_floor_4": {
      "frame": { "x": 96, "y": 80, "w": 16, "h": 16 },
      "rotated": false,
      "trimmed": false,
      "spriteSourceSize": { "x": 0, "y": 0, "w": 16, "h": 16 },
      "sourceSize": { "w": 16, "h": 16 }
    },
    "orange_floor_5": {
      "frame": { "x": 112, "y": 80, "w": 16, "h": 16 },
      "rotated": false,
      "trimmed": false,
      "spriteSourceSize": { "x": 0, "y": 0, "w": 16, "h": 16 },
      "sourceSize": { "w": 16, "h": 16 }
    },
    "orange_floor_6": {
      "frame": { "x": 128, "y": 80, "w": 16, "h": 16 },
      "rotated": false,
      "trimmed": false,
      "spriteSourceSize": { "x": 0, "y": 0, "w": 16, "h": 16 },
      "sourceSize": { "w": 16, "h": 16 }
    },
    "orange_floor_lower_left": {
      "frame": { "x": 144, "y": 80, "w": 16, "h": 16 },
      "rotated": false,
      "trimmed": false,
      "spriteSourceSize": { "x": 0, "y": 0, "w": 16, "h": 16 },
      "sourceSize": { "w": 16, "h": 16 }
    },
    "orange_floor_lower_right": {
      "frame": { "x": 160, "y": 80, "w": 16, "h": 16 },
      "rotated": false,
      "trimmed": false,
      "spriteSourceSize": { "x": 0, "y": 0, "w": 16, "h": 16 },
      "sourceSize": { "w": 16, "h": 16 }
    },
    "metal_brick_mini": {
      "frame": { "x": 192, "y": 80, "w": 16, "h": 16 },
      "rotated": false,
      "trimmed": false,
      "spriteSourceSize": { "x": 0, "y": 0, "w": 16, "h": 16 },
      "sourceSize": { "w": 16, "h": 16 }
    },
    "metal_brick_upper_left": {
      "frame": { "x": 208, "y": 80, "w": 16, "h": 16 },
      "rotated": false,
      "trimmed": false,
      "spriteSourceSize": { "x": 0, "y": 0, "w": 16, "h": 16 },
      "sourceSize": { "w": 16, "h": 16 }
    },
    "metal_brick_upper_right": {
      "frame": { "x": 224, "y": 80, "w": 16, "h": 16 },
      "rotated": false,
      "trimmed": false,
      "spriteSourceSize": { "x": 0, "y": 0, "w": 16, "h": 16 },
      "sourceSize": { "w": 16, "h": 16 }
    },
    "metal_brick_v_2": {
      "frame": { "x": 240, "y": 80, "w": 16, "h": 16 },
      "rotated": false,
      "trimmed": false,
      "spriteSourceSize": { "x": 0, "y": 0, "w": 16, "h": 16 },
      "sourceSize": { "w": 16, "h": 16 }
    },
    "brick_4": {
      "frame": { "x": 272, "y": 80, "w": 16, "h": 16 },
      "rotated": false,
      "trimmed": false,
      "spriteSourceSize": { "x": 0, "y": 0, "w": 16, "h": 16 },
      "sourceSize": { "w": 16, "h": 16 }
    },
    "brick_5": {
      "frame": { "x": 288, "y": 80, "w": 16, "h": 16 },
      "rotated": false,
      "trimmed": false,
      "spriteSourceSize": { "x": 0, "y": 0, "w": 16, "h": 16 },
      "sourceSize": { "w": 16, "h": 16 }
    },
    "brick_6": {
      "frame": { "x": 304, "y": 80, "w": 16, "h": 16 },
      "rotated": false,
      "trimmed": false,
      "spriteSourceSize": { "x": 0, "y": 0, "w": 16, "h": 16 },
      "sourceSize": { "w": 16, "h": 16 }
    },
    "sprite96": {
      "frame": { "x": 320, "y": 80, "w": 16, "h": 16 },
      "rotated": false,
      "trimmed": false,
      "spriteSourceSize": { "x": 0, "y": 0, "w": 16, "h": 16 },
      "sourceSize": { "w": 16, "h": 16 }
    },
    "sprite97": {
      "frame": { "x": 336, "y": 80, "w": 16, "h": 16 },
      "rotated": false,
      "trimmed": false,
      "spriteSourceSize": { "x": 0, "y": 0, "w": 16, "h": 16 },
      "sourceSize": { "w": 16, "h": 16 }
    },
    "wood_lower_left_corner": {
      "frame": { "x": 0, "y": 96, "w": 16, "h": 16 },
      "rotated": false,
      "trimmed": false,
      "spriteSourceSize": { "x": 0, "y": 0, "w": 16, "h": 16 },
      "sourceSize": { "w": 16, "h": 16 }
    },
    "wood_bottom": {
      "frame": { "x": 16, "y": 96, "w": 16, "h": 16 },
      "rotated": false,
      "trimmed": false,
      "spriteSourceSize": { "x": 0, "y": 0, "w": 16, "h": 16 },
      "sourceSize": { "w": 16, "h": 16 }
    },
    "wood_lower_right_corner": {
      "frame": { "x": 32, "y": 96, "w": 16, "h": 16 },
      "rotated": false,
      "trimmed": false,
      "spriteSourceSize": { "x": 0, "y": 0, "w": 16, "h": 16 },
      "sourceSize": { "w": 16, "h": 16 }
    },
    "orange_floor_7": {
      "frame": { "x": 96, "y": 96, "w": 16, "h": 16 },
      "rotated": false,
      "trimmed": false,
      "spriteSourceSize": { "x": 0, "y": 0, "w": 16, "h": 16 },
      "sourceSize": { "w": 16, "h": 16 }
    },
    "orange_floor_8": {
      "frame": { "x": 112, "y": 96, "w": 16, "h": 16 },
      "rotated": false,
      "trimmed": false,
      "spriteSourceSize": { "x": 0, "y": 0, "w": 16, "h": 16 },
      "sourceSize": { "w": 16, "h": 16 }
    },
    "orange_floor_9": {
      "frame": { "x": 128, "y": 96, "w": 16, "h": 16 },
      "rotated": false,
      "trimmed": false,
      "spriteSourceSize": { "x": 0, "y": 0, "w": 16, "h": 16 },
      "sourceSize": { "w": 16, "h": 16 }
    },
    "metal_brick_lower_left": {
      "frame": { "x": 208, "y": 96, "w": 16, "h": 16 },
      "rotated": false,
      "trimmed": false,
      "spriteSourceSize": { "x": 0, "y": 0, "w": 16, "h": 16 },
      "sourceSize": { "w": 16, "h": 16 }
    },
    "metal_brick_lower_right": {
      "frame": { "x": 224, "y": 96, "w": 16, "h": 16 },
      "rotated": false,
      "trimmed": false,
      "spriteSourceSize": { "x": 0, "y": 0, "w": 16, "h": 16 },
      "sourceSize": { "w": 16, "h": 16 }
    },
    "metal_brick_v_3": {
      "frame": { "x": 240, "y": 96, "w": 16, "h": 16 },
      "rotated": false,
      "trimmed": false,
      "spriteSourceSize": { "x": 0, "y": 0, "w": 16, "h": 16 },
      "sourceSize": { "w": 16, "h": 16 }
    },
    "brick_7": {
      "frame": { "x": 272, "y": 96, "w": 16, "h": 16 },
      "rotated": false,
      "trimmed": false,
      "spriteSourceSize": { "x": 0, "y": 0, "w": 16, "h": 16 },
      "sourceSize": { "w": 16, "h": 16 }
    },
    "brick_8": {
      "frame": { "x": 288, "y": 96, "w": 16, "h": 16 },
      "rotated": false,
      "trimmed": false,
      "spriteSourceSize": { "x": 0, "y": 0, "w": 16, "h": 16 },
      "sourceSize": { "w": 16, "h": 16 }
    },
    "brick_9": {
      "frame": { "x": 304, "y": 96, "w": 16, "h": 16 },
      "rotated": false,
      "trimmed": false,
      "spriteSourceSize": { "x": 0, "y": 0, "w": 16, "h": 16 },
      "sourceSize": { "w": 16, "h": 16 }
    },
    "grass_upper_left_corner": {
      "frame": { "x": 0, "y": 128, "w": 16, "h": 16 },
      "rotated": false,
      "trimmed": false,
      "spriteSourceSize": { "x": 0, "y": 0, "w": 16, "h": 16 },
      "sourceSize": { "w": 16, "h": 16 }
    },
    "grass_top": {
      "frame": { "x": 16, "y": 128, "w": 16, "h": 16 },
      "rotated": false,
      "trimmed": false,
      "spriteSourceSize": { "x": 0, "y": 0, "w": 16, "h": 16 },
      "sourceSize": { "w": 16, "h": 16 }
    },
    "grass_upper_right_corner": {
      "frame": { "x": 32, "y": 128, "w": 16, "h": 16 },
      "rotated": false,
      "trimmed": false,
      "spriteSourceSize": { "x": 0, "y": 0, "w": 16, "h": 16 },
      "sourceSize": { "w": 16, "h": 16 }
    },
    "sprite113": {
      "frame": { "x": 48, "y": 128, "w": 16, "h": 16 },
      "rotated": false,
      "trimmed": false,
      "spriteSourceSize": { "x": 0, "y": 0, "w": 16, "h": 16 },
      "sourceSize": { "w": 16, "h": 16 }
    },
    "sprite114": {
      "frame": { "x": 64, "y": 128, "w": 16, "h": 16 },
      "rotated": false,
      "trimmed": false,
      "spriteSourceSize": { "x": 0, "y": 0, "w": 16, "h": 16 },
      "sourceSize": { "w": 16, "h": 16 }
    },
    "pink_floor_1": {
      "frame": { "x": 96, "y": 128, "w": 16, "h": 16 },
      "rotated": false,
      "trimmed": false,
      "spriteSourceSize": { "x": 0, "y": 0, "w": 16, "h": 16 },
      "sourceSize": { "w": 16, "h": 16 }
    },
    "pink_floor_2": {
      "frame": { "x": 112, "y": 128, "w": 16, "h": 16 },
      "rotated": false,
      "trimmed": false,
      "spriteSourceSize": { "x": 0, "y": 0, "w": 16, "h": 16 },
      "sourceSize": { "w": 16, "h": 16 }
    },
    "pink_floor_3": {
      "frame": { "x": 128, "y": 128, "w": 16, "h": 16 },
      "rotated": false,
      "trimmed": false,
      "spriteSourceSize": { "x": 0, "y": 0, "w": 16, "h": 16 },
      "sourceSize": { "w": 16, "h": 16 }
    },
    "pink_floor_upper_left": {
      "frame": { "x": 144, "y": 128, "w": 16, "h": 16 },
      "rotated": false,
      "trimmed": false,
      "spriteSourceSize": { "x": 0, "y": 0, "w": 16, "h": 16 },
      "sourceSize": { "w": 16, "h": 16 }
    },
    "pink_floor_upper_right": {
      "frame": { "x": 160, "y": 128, "w": 16, "h": 16 },
      "rotated": false,
      "trimmed": false,
      "spriteSourceSize": { "x": 0, "y": 0, "w": 16, "h": 16 },
      "sourceSize": { "w": 16, "h": 16 }
    },
    "orange_brick_h_1": {
      "frame": { "x": 192, "y": 128, "w": 16, "h": 16 },
      "rotated": false,
      "trimmed": false,
      "spriteSourceSize": { "x": 0, "y": 0, "w": 16, "h": 16 },
      "sourceSize": { "w": 16, "h": 16 }
    },
    "orange_brick_h_2": {
      "frame": { "x": 208, "y": 128, "w": 16, "h": 16 },
      "rotated": false,
      "trimmed": false,
      "spriteSourceSize": { "x": 0, "y": 0, "w": 16, "h": 16 },
      "sourceSize": { "w": 16, "h": 16 }
    },
    "orange_brick_h_3": {
      "frame": { "x": 224, "y": 128, "w": 16, "h": 16 },
      "rotated": false,
      "trimmed": false,
      "spriteSourceSize": { "x": 0, "y": 0, "w": 16, "h": 16 },
      "sourceSize": { "w": 16, "h": 16 }
    },
    "orange_brick_v_1": {
      "frame": { "x": 240, "y": 128, "w": 16, "h": 16 },
      "rotated": false,
      "trimmed": false,
      "spriteSourceSize": { "x": 0, "y": 0, "w": 16, "h": 16 },
      "sourceSize": { "w": 16, "h": 16 }
    },
    "yellow_brick_h_1": {
      "frame": { "x": 272, "y": 128, "w": 16, "h": 16 },
      "rotated": false,
      "trimmed": false,
      "spriteSourceSize": { "x": 0, "y": 0, "w": 16, "h": 16 },
      "sourceSize": { "w": 16, "h": 16 }
    },
    "yellow_brick_h_2": {
      "frame": { "x": 288, "y": 128, "w": 16, "h": 16 },
      "rotated": false,
      "trimmed": false,
      "spriteSourceSize": { "x": 0, "y": 0, "w": 16, "h": 16 },
      "sourceSize": { "w": 16, "h": 16 }
    },
    "yellow_brick_h_3": {
      "frame": { "x": 304, "y": 128, "w": 16, "h": 16 },
      "rotated": false,
      "trimmed": false,
      "spriteSourceSize": { "x": 0, "y": 0, "w": 16, "h": 16 },
      "sourceSize": { "w": 16, "h": 16 }
    },
    "yellow_brick_v_": {
      "frame": { "x": 320, "y": 128, "w": 16, "h": 16 },
      "rotated": false,
      "trimmed": false,
      "spriteSourceSize": { "x": 0, "y": 0, "w": 16, "h": 16 },
      "sourceSize": { "w": 16, "h": 16 }
    },
    "grass_left": {
      "frame": { "x": 0, "y": 144, "w": 16, "h": 16 },
      "rotated": false,
      "trimmed": false,
      "spriteSourceSize": { "x": 0, "y": 0, "w": 16, "h": 16 },
      "sourceSize": { "w": 16, "h": 16 }
    },
    "sprite129": {
      "frame": { "x": 16, "y": 144, "w": 16, "h": 16 },
      "rotated": false,
      "trimmed": false,
      "spriteSourceSize": { "x": 0, "y": 0, "w": 16, "h": 16 },
      "sourceSize": { "w": 16, "h": 16 }
    },
    "grass_right": {
      "frame": { "x": 32, "y": 144, "w": 16, "h": 16 },
      "rotated": false,
      "trimmed": false,
      "spriteSourceSize": { "x": 0, "y": 0, "w": 16, "h": 16 },
      "sourceSize": { "w": 16, "h": 16 }
    },
    "sprite131": {
      "frame": { "x": 48, "y": 144, "w": 16, "h": 16 },
      "rotated": false,
      "trimmed": false,
      "spriteSourceSize": { "x": 0, "y": 0, "w": 16, "h": 16 },
      "sourceSize": { "w": 16, "h": 16 }
    },
    "sprite132": {
      "frame": { "x": 64, "y": 144, "w": 16, "h": 16 },
      "rotated": false,
      "trimmed": false,
      "spriteSourceSize": { "x": 0, "y": 0, "w": 16, "h": 16 },
      "sourceSize": { "w": 16, "h": 16 }
    },
    "pink_floor_4": {
      "frame": { "x": 96, "y": 144, "w": 16, "h": 16 },
      "rotated": false,
      "trimmed": false,
      "spriteSourceSize": { "x": 0, "y": 0, "w": 16, "h": 16 },
      "sourceSize": { "w": 16, "h": 16 }
    },
    "pink_floor_5": {
      "frame": { "x": 112, "y": 144, "w": 16, "h": 16 },
      "rotated": false,
      "trimmed": false,
      "spriteSourceSize": { "x": 0, "y": 0, "w": 16, "h": 16 },
      "sourceSize": { "w": 16, "h": 16 }
    },
    "pink_floor_6": {
      "frame": { "x": 128, "y": 144, "w": 16, "h": 16 },
      "rotated": false,
      "trimmed": false,
      "spriteSourceSize": { "x": 0, "y": 0, "w": 16, "h": 16 },
      "sourceSize": { "w": 16, "h": 16 }
    },
    "pink_floor_lower_left": {
      "frame": { "x": 144, "y": 144, "w": 16, "h": 16 },
      "rotated": false,
      "trimmed": false,
      "spriteSourceSize": { "x": 0, "y": 0, "w": 16, "h": 16 },
      "sourceSize": { "w": 16, "h": 16 }
    },
    "pink_floor_lower_right": {
      "frame": { "x": 160, "y": 144, "w": 16, "h": 16 },
      "rotated": false,
      "trimmed": false,
      "spriteSourceSize": { "x": 0, "y": 0, "w": 16, "h": 16 },
      "sourceSize": { "w": 16, "h": 16 }
    },
    "orange_brick_mini": {
      "frame": { "x": 192, "y": 144, "w": 16, "h": 16 },
      "rotated": false,
      "trimmed": false,
      "spriteSourceSize": { "x": 0, "y": 0, "w": 16, "h": 16 },
      "sourceSize": { "w": 16, "h": 16 }
    },
    "orange_brick_upper_left": {
      "frame": { "x": 208, "y": 144, "w": 16, "h": 16 },
      "rotated": false,
      "trimmed": false,
      "spriteSourceSize": { "x": 0, "y": 0, "w": 16, "h": 16 },
      "sourceSize": { "w": 16, "h": 16 }
    },
    "orange_brick_upper_right": {
      "frame": { "x": 224, "y": 144, "w": 16, "h": 16 },
      "rotated": false,
      "trimmed": false,
      "spriteSourceSize": { "x": 0, "y": 0, "w": 16, "h": 16 },
      "sourceSize": { "w": 16, "h": 16 }
    },
    "orange_brick_v_2": {
      "frame": { "x": 240, "y": 144, "w": 16, "h": 16 },
      "rotated": false,
      "trimmed": false,
      "spriteSourceSize": { "x": 0, "y": 0, "w": 16, "h": 16 },
      "sourceSize": { "w": 16, "h": 16 }
    },
    "yellow_brick_mini": {
      "frame": { "x": 272, "y": 144, "w": 16, "h": 16 },
      "rotated": false,
      "trimmed": false,
      "spriteSourceSize": { "x": 0, "y": 0, "w": 16, "h": 16 },
      "sourceSize": { "w": 16, "h": 16 }
    },
    "yellow_brick_upper_left": {
      "frame": { "x": 288, "y": 144, "w": 16, "h": 16 },
      "rotated": false,
      "trimmed": false,
      "spriteSourceSize": { "x": 0, "y": 0, "w": 16, "h": 16 },
      "sourceSize": { "w": 16, "h": 16 }
    },
    "yellow_brick_upper_right": {
      "frame": { "x": 304, "y": 144, "w": 16, "h": 16 },
      "rotated": false,
      "trimmed": false,
      "spriteSourceSize": { "x": 0, "y": 0, "w": 16, "h": 16 },
      "sourceSize": { "w": 16, "h": 16 }
    },
    "yellow_brick_v_2": {
      "frame": { "x": 320, "y": 144, "w": 16, "h": 16 },
      "rotated": false,
      "trimmed": false,
      "spriteSourceSize": { "x": 0, "y": 0, "w": 16, "h": 16 },
      "sourceSize": { "w": 16, "h": 16 }
    },
    "grass_lower_left_corner": {
      "frame": { "x": 0, "y": 160, "w": 16, "h": 16 },
      "rotated": false,
      "trimmed": false,
      "spriteSourceSize": { "x": 0, "y": 0, "w": 16, "h": 16 },
      "sourceSize": { "w": 16, "h": 16 }
    },
    "sprite147": {
      "frame": { "x": 16, "y": 160, "w": 16, "h": 16 },
      "rotated": false,
      "trimmed": false,
      "spriteSourceSize": { "x": 0, "y": 0, "w": 16, "h": 16 },
      "sourceSize": { "w": 16, "h": 16 }
    },
    "grass_lower_right_corner": {
      "frame": { "x": 32, "y": 160, "w": 16, "h": 16 },
      "rotated": false,
      "trimmed": false,
      "spriteSourceSize": { "x": 0, "y": 0, "w": 16, "h": 16 },
      "sourceSize": { "w": 16, "h": 16 }
    },
    "pink_floor_7": {
      "frame": { "x": 96, "y": 160, "w": 16, "h": 16 },
      "rotated": false,
      "trimmed": false,
      "spriteSourceSize": { "x": 0, "y": 0, "w": 16, "h": 16 },
      "sourceSize": { "w": 16, "h": 16 }
    },
    "pink_floor_8": {
      "frame": { "x": 112, "y": 160, "w": 16, "h": 16 },
      "rotated": false,
      "trimmed": false,
      "spriteSourceSize": { "x": 0, "y": 0, "w": 16, "h": 16 },
      "sourceSize": { "w": 16, "h": 16 }
    },
    "pink_floor_9": {
      "frame": { "x": 128, "y": 160, "w": 16, "h": 16 },
      "rotated": false,
      "trimmed": false,
      "spriteSourceSize": { "x": 0, "y": 0, "w": 16, "h": 16 },
      "sourceSize": { "w": 16, "h": 16 }
    },
    "orange_brick_lower_left": {
      "frame": { "x": 208, "y": 160, "w": 16, "h": 16 },
      "rotated": false,
      "trimmed": false,
      "spriteSourceSize": { "x": 0, "y": 0, "w": 16, "h": 16 },
      "sourceSize": { "w": 16, "h": 16 }
    },
    "orange_brick_lower_right": {
      "frame": { "x": 224, "y": 160, "w": 16, "h": 16 },
      "rotated": false,
      "trimmed": false,
      "spriteSourceSize": { "x": 0, "y": 0, "w": 16, "h": 16 },
      "sourceSize": { "w": 16, "h": 16 }
    },
    "orange_brick_v_3": {
      "frame": { "x": 240, "y": 160, "w": 16, "h": 16 },
      "rotated": false,
      "trimmed": false,
      "spriteSourceSize": { "x": 0, "y": 0, "w": 16, "h": 16 },
      "sourceSize": { "w": 16, "h": 16 }
    },
    "yellow_brick_lower_left": {
      "frame": { "x": 288, "y": 160, "w": 16, "h": 16 },
      "rotated": false,
      "trimmed": false,
      "spriteSourceSize": { "x": 0, "y": 0, "w": 16, "h": 16 },
      "sourceSize": { "w": 16, "h": 16 }
    },
    "yellow_brick_lower_right": {
      "frame": { "x": 304, "y": 160, "w": 16, "h": 16 },
      "rotated": false,
      "trimmed": false,
      "spriteSourceSize": { "x": 0, "y": 0, "w": 16, "h": 16 },
      "sourceSize": { "w": 16, "h": 16 }
    },
    "yellow_brick_v_3": {
      "frame": { "x": 320, "y": 160, "w": 16, "h": 16 },
      "rotated": false,
      "trimmed": false,
      "spriteSourceSize": { "x": 0, "y": 0, "w": 16, "h": 16 },
      "sourceSize": { "w": 16, "h": 16 }
    }
  },
  "meta": {
    "app": "https://www.leshylabs.com/apps/sstool/",
    "version": "Leshy SpriteSheet Tool v0.8.4",
    "image": "terrain.png",
    "size": { "w": 352, "h": 176 },
    "scale": 1
  }
}
